{
   "_typeName" : "ObjectConstruct",
   "_version" : "VER3",
   "animations" : [],
   "finder" : {
      "_typeName" : "FindableGeometryElement",
      "geom" : {
         "_typeName" : "IdenticGeometry"
      }
   },
   "id" : 0,
   "position" : {
      "_typeName" : "PositionElement",
      "angle" : 0,
      "offset" : [ 0, 0 ],
      "scaleX" : 1,
      "scaleY" : 1
   },
   "selector" : {
      "_typeName" : "PressableAndClickableElement",
      "clickTime" : 500
   },
   "skin" : {
      "_typeName" : "StaticTextureRect",
      "box" : {
         "_typeName" : "PixelBox",
         "height" : 8,
         "width" : 8
      },
      "color" : [ 1, 1, 1, 1 ],
      "imageName" : "pacman/coin.png",
      "position" : {
         "_typeName" : "AligningOffset",
         "horAlign" : 1,
         "horOffset" : {
            "_typeName" : "RelativeValue",
            "type" : 1,
            "value" : 0
         },
         "vertAlign" : 1,
         "vertOffset" : {
            "_typeName" : "RelativeValue",
            "type" : 1,
            "value" : 0
         }
      }
   },
   "transitionAnimations" : []
}
