{
   "_typeName" : "CanvasLayout",
   "_version" : "VER3",
   "adjustment" : 0,
   "box" : {
      "_typeName" : "RelativeBox",
      "height" : {
         "_typeName" : "RelativeValue",
         "type" : 0,
         "value" : 0
      },
      "offset" : {
         "_empty" : true
      },
      "width" : {
         "_typeName" : "RelativeValue",
         "type" : 0,
         "value" : 0
      }
   },
   "list" : [
      {
         "_typeName" : "LinearLayout",
         "list" : [
            {
               "_typeName" : "CanvasLayout",
               "adjustment" : 0,
               "box" : {
                  "_typeName" : "RelativeBox",
                  "height" : {
                     "_typeName" : "RelativeValue",
                     "type" : 0,
                     "value" : 0
                  },
                  "offset" : {
                     "_empty" : true
                  },
                  "width" : {
                     "_typeName" : "RelativeValue",
                     "type" : 2,
                     "value" : 0.699999988079071
                  }
               },
               "list" : [
                  {
                     "_typeName" : "CanvasLayout",
                     "adjustment" : 0,
                     "box" : {
                        "_typeName" : "SquareBox"
                     },
                     "list" : [
                        {
                           "_name" : "background",
                           "_typeName" : "StaticTextureRect",
                           "box" : {
                              "_typeName" : "RelativeBox",
                              "height" : {
                                 "_typeName" : "RelativeValue",
                                 "type" : 0,
                                 "value" : 0
                              },
                              "offset" : {
                                 "_empty" : true
                              },
                              "width" : {
                                 "_typeName" : "RelativeValue",
                                 "type" : 0,
                                 "value" : 0
                              }
                           },
                           "color" : [ 1, 1, 1, 0.1568627506494522 ],
                           "imageName" : "",
                           "position" : {
                              "_typeName" : "AligningOffset",
                              "horAlign" : 1,
                              "horOffset" : {
                                 "_typeName" : "RelativeValue",
                                 "type" : 1,
                                 "value" : 0
                              },
                              "vertAlign" : 1,
                              "vertOffset" : {
                                 "_typeName" : "RelativeValue",
                                 "type" : 1,
                                 "value" : 0
                              }
                           }
                        },
                        {
                           "_name" : "polygon",
                           "_typeName" : "TexturedPolygon",
                           "box" : {
                              "_typeName" : "RelativeBox",
                              "height" : {
                                 "_typeName" : "RelativeValue",
                                 "type" : 0,
                                 "value" : 0
                              },
                              "offset" : {
                                 "_empty" : true
                              },
                              "width" : {
                                 "_typeName" : "RelativeValue",
                                 "type" : 0,
                                 "value" : 0
                              }
                           },
                           "imageName" : "",
                           "innerRings" : [],
                           "outerRing" : [],
                           "position" : {
                              "_typeName" : "AligningOffset",
                              "horAlign" : 1,
                              "horOffset" : {
                                 "_typeName" : "RelativeValue",
                                 "type" : 1,
                                 "value" : 0
                              },
                              "vertAlign" : 1,
                              "vertOffset" : {
                                 "_typeName" : "RelativeValue",
                                 "type" : 1,
                                 "value" : 0
                              }
                           }
                        },
                        {
                           "_name" : "field",
                           "_typeName" : "GameView",
                           "box" : {
                              "_typeName" : "RelativeBox",
                              "height" : {
                                 "_typeName" : "RelativeValue",
                                 "type" : 0,
                                 "value" : 0
                              },
                              "offset" : {
                                 "_empty" : true
                              },
                              "width" : {
                                 "_typeName" : "RelativeValue",
                                 "type" : 0,
                                 "value" : 0
                              }
                           },
                           "list" : [
                              {
                                 "_name" : "verticesLayer",
                                 "_typeName" : "Layer",
                                 "index" : {
                                    "_typeName" : "FlatIndex",
                                    "keyType" : 2
                                 },
                                 "list" : [],
                                 "order" : {
                                    "_typeName" : "SortByIDOrder"
                                 }
                              }
                           ],
                           "position" : {
                              "_typeName" : "AligningOffset",
                              "horAlign" : 1,
                              "horOffset" : {
                                 "_typeName" : "RelativeValue",
                                 "type" : 1,
                                 "value" : 0
                              },
                              "vertAlign" : 1,
                              "vertOffset" : {
                                 "_typeName" : "RelativeValue",
                                 "type" : 1,
                                 "value" : 0
                              }
                           }
                        }
                     ],
                     "position" : {
                        "_typeName" : "AligningOffset",
                        "horAlign" : 1,
                        "horOffset" : {
                           "_typeName" : "RelativeValue",
                           "type" : 1,
                           "value" : 0
                        },
                        "vertAlign" : 1,
                        "vertOffset" : {
                           "_typeName" : "RelativeValue",
                           "type" : 1,
                           "value" : 0
                        }
                     }
                  }
               ],
               "position" : {
                  "_typeName" : "AligningOffset",
                  "horAlign" : 0,
                  "horOffset" : {
                     "_typeName" : "RelativeValue",
                     "type" : 1,
                     "value" : 0
                  },
                  "vertAlign" : 1,
                  "vertOffset" : {
                     "_typeName" : "RelativeValue",
                     "type" : 1,
                     "value" : 0
                  }
               }
            },
            {
               "_typeName" : "CanvasLayout",
               "adjustment" : 0,
               "box" : {
                  "_typeName" : "RelativeBox",
                  "height" : {
                     "_typeName" : "RelativeValue",
                     "type" : 0,
                     "value" : 0
                  },
                  "offset" : {
                     "_empty" : true
                  },
                  "width" : {
                     "_typeName" : "RelativeValue",
                     "type" : 0,
                     "value" : 0
                  }
               },
               "list" : [
                  {
                     "_typeName" : "LinearLayout",
                     "list" : [
                        {
                           "_name" : "imagePathBox",
                           "_typeName" : "TextBox",
                           "filter" : {
                              "_empty" : true
                           },
                           "position" : {
                              "_typeName" : "AligningOffset",
                              "horAlign" : 0,
                              "horOffset" : {
                                 "_typeName" : "RelativeValue",
                                 "type" : 1,
                                 "value" : 0
                              },
                              "vertAlign" : 0,
                              "vertOffset" : {
                                 "_typeName" : "RelativeValue",
                                 "type" : 1,
                                 "value" : 0
                              }
                           },
                           "skin" : {
                              "_typeName" : "SimpleRectangleTextBoxSkin",
                              "borderColor" : [ 0.196078434586525, 0.1568627506494522, 0.7058823704719543, 1 ],
                              "borderWidth" : 1,
                              "box" : {
                                 "_typeName" : "PixelBox",
                                 "height" : 48,
                                 "width" : 300
                              },
                              "fillColor" : [ 1, 1, 1, 1 ],
                              "font" : {
                                 "_typeName" : "FontDesc",
                                 "family" : "Roboto",
                                 "size" : 20
                              },
                              "selectionColor" : [ 0.7450980544090271, 0.8235294222831726, 1, 1 ],
                              "textColor" : [ 0, 0, 0, 1 ],
                              "textOutlineColor" : [ 1, 1, 1, 1 ]
                           },
                           "text" : ""
                        },
                        {
                           "_name" : "updateButton",
                           "_typeName" : "Button",
                           "position" : {
                              "_typeName" : "AligningOffset",
                              "horAlign" : 0,
                              "horOffset" : {
                                 "_typeName" : "RelativeValue",
                                 "type" : 1,
                                 "value" : 0
                              },
                              "vertAlign" : 0,
                              "vertOffset" : {
                                 "_typeName" : "RelativeValue",
                                 "type" : 1,
                                 "value" : -10
                              }
                           },
                           "skin" : {
                              "_typeName" : "SimpleRectangleButtonSkin",
                              "borderColor" : [ 0, 0, 0, 1 ],
                              "borderWidth" : 1,
                              "box" : {
                                 "_typeName" : "PixelBox",
                                 "height" : 48,
                                 "width" : 300
                              },
                              "fillColor" : [ 0.7843137383460999, 0.7843137383460999, 0.7843137383460999, 1 ],
                              "font" : {
                                 "_typeName" : "FontDesc",
                                 "family" : "Roboto",
                                 "outlineWidth" : 1,
                                 "size" : 28
                              },
                              "text" : "Обновить",
                              "textColor" : [ 0, 0, 0, 1 ],
                              "textOutlineColor" : [ 1, 1, 1, 1 ],
                              "useGradient" : true
                           }
                        },
                        {
                           "_name" : "clearButton",
                           "_typeName" : "Button",
                           "position" : {
                              "_typeName" : "AligningOffset",
                              "horAlign" : 0,
                              "horOffset" : {
                                 "_typeName" : "RelativeValue",
                                 "type" : 1,
                                 "value" : 0
                              },
                              "vertAlign" : 0,
                              "vertOffset" : {
                                 "_typeName" : "RelativeValue",
                                 "type" : 1,
                                 "value" : -10
                              }
                           },
                           "skin" : {
                              "_typeName" : "SimpleRectangleButtonSkin",
                              "borderColor" : [ 0, 0, 0, 1 ],
                              "borderWidth" : 1,
                              "box" : {
                                 "_typeName" : "PixelBox",
                                 "height" : 48,
                                 "width" : 300
                              },
                              "fillColor" : [ 0.7843137383460999, 0.7843137383460999, 0.7843137383460999, 1 ],
                              "font" : {
                                 "_typeName" : "FontDesc",
                                 "family" : "Roboto",
                                 "outlineWidth" : 1,
                                 "size" : 28
                              },
                              "text" : "Очистить",
                              "textColor" : [ 0, 0, 0, 1 ],
                              "textOutlineColor" : [ 1, 1, 1, 1 ],
                              "useGradient" : true
                           }
                        },
                        {
                           "_typeName" : "LinearLayout",
                           "list" : [
                              {
                                 "_name" : "showBackgroundCheckBox",
                                 "_typeName" : "CheckBox",
                                 "checked" : true,
                                 "position" : {
                                    "_typeName" : "AligningOffset",
                                    "horAlign" : 0,
                                    "horOffset" : {
                                       "_typeName" : "RelativeValue",
                                       "type" : 1,
                                       "value" : 0
                                    },
                                    "vertAlign" : 2,
                                    "vertOffset" : {
                                       "_typeName" : "RelativeValue",
                                       "type" : 1,
                                       "value" : 0
                                    }
                                 },
                                 "skin" : {
                                    "_typeName" : "RectangleCheckBoxSkin",
                                    "borderColor" : [ 0, 0, 0, 1 ],
                                    "borderWidth" : 1,
                                    "box" : {
                                       "_typeName" : "PixelBox",
                                       "height" : 32,
                                       "width" : 32
                                    },
                                    "checkImageColor" : [ 0, 0, 0, 1 ],
                                    "checkImageHeight" : 24,
                                    "checkImageName" : "",
                                    "checkImageWidth" : 24,
                                    "fillColor" : [ 1, 1, 1, 1 ]
                                 }
                              },
                              {
                                 "_typeName" : "StaticLabel",
                                 "adjustSize" : true,
                                 "box" : {
                                    "_typeName" : "RelativeBox",
                                    "height" : {
                                       "_typeName" : "RelativeValue",
                                       "type" : 0,
                                       "value" : 0
                                    },
                                    "offset" : {
                                       "_empty" : true
                                    },
                                    "width" : {
                                       "_typeName" : "RelativeValue",
                                       "type" : 0,
                                       "value" : 0
                                    }
                                 },
                                 "color" : [ 0, 0, 0, 1 ],
                                 "outlineColor" : [ 1, 1, 1, 1 ],
                                 "position" : {
                                    "_typeName" : "AligningOffset",
                                    "horAlign" : 0,
                                    "horOffset" : {
                                       "_typeName" : "RelativeValue",
                                       "type" : 1,
                                       "value" : 10
                                    },
                                    "vertAlign" : 2,
                                    "vertOffset" : {
                                       "_typeName" : "RelativeValue",
                                       "type" : 1,
                                       "value" : 0
                                    }
                                 },
                                 "properties" : {
                                    "_typeName" : "AlignProperties",
                                    "enableStacking" : false,
                                    "font" : {
                                       "_typeName" : "FontDesc",
                                       "family" : "Roboto",
                                       "size" : 28
                                    },
                                    "horAlign" : 0,
                                    "vertAlign" : 0
                                 },
                                 "text" : "Надпись"
                              }
                           ],
                           "position" : {
                              "_typeName" : "AligningOffset",
                              "horAlign" : 0,
                              "horOffset" : {
                                 "_typeName" : "RelativeValue",
                                 "type" : 1,
                                 "value" : 0
                              },
                              "vertAlign" : 0,
                              "vertOffset" : {
                                 "_typeName" : "RelativeValue",
                                 "type" : 1,
                                 "value" : -10
                              }
                           },
                           "skin" : {
                              "_typeName" : "HorizontalLayoutSkin",
                              "adjustment" : 1,
                              "align" : 2,
                              "box" : {
                                 "_typeName" : "RelativeBox",
                                 "height" : {
                                    "_typeName" : "RelativeValue",
                                    "type" : 0,
                                    "value" : 0
                                 },
                                 "offset" : {
                                    "_empty" : true
                                 },
                                 "width" : {
                                    "_typeName" : "RelativeValue",
                                    "type" : 0,
                                    "value" : 0
                                 }
                              },
                              "padding" : {
                                 "_typeName" : "RelativeValue",
                                 "type" : 1,
                                 "value" : 10
                              }
                           },
                           "skipInvisibleElements" : false
                        }
                     ],
                     "position" : {
                        "_typeName" : "AligningOffset",
                        "horAlign" : 1,
                        "horOffset" : {
                           "_typeName" : "RelativeValue",
                           "type" : 1,
                           "value" : 0
                        },
                        "vertAlign" : 1,
                        "vertOffset" : {
                           "_typeName" : "RelativeValue",
                           "type" : 1,
                           "value" : 0
                        }
                     },
                     "skin" : {
                        "_typeName" : "VerticalLayoutSkin",
                        "adjustment" : 1,
                        "align" : 0,
                        "box" : {
                           "_typeName" : "RelativeBox",
                           "height" : {
                              "_typeName" : "RelativeValue",
                              "type" : 0,
                              "value" : 0
                           },
                           "offset" : {
                              "_empty" : true
                           },
                           "width" : {
                              "_typeName" : "RelativeValue",
                              "type" : 0,
                              "value" : 0
                           }
                        },
                        "padding" : {
                           "_typeName" : "RelativeValue",
                           "type" : 1,
                           "value" : -10
                        }
                     },
                     "skipInvisibleElements" : false
                  }
               ],
               "position" : {
                  "_typeName" : "AligningOffset",
                  "horAlign" : 0,
                  "horOffset" : {
                     "_typeName" : "RelativeValue",
                     "type" : 1,
                     "value" : 0
                  },
                  "vertAlign" : 1,
                  "vertOffset" : {
                     "_typeName" : "RelativeValue",
                     "type" : 1,
                     "value" : 0
                  }
               }
            }
         ],
         "position" : {
            "_typeName" : "AligningOffset",
            "horAlign" : 1,
            "horOffset" : {
               "_typeName" : "RelativeValue",
               "type" : 1,
               "value" : 0
            },
            "vertAlign" : 1,
            "vertOffset" : {
               "_typeName" : "RelativeValue",
               "type" : 1,
               "value" : 0
            }
         },
         "skin" : {
            "_typeName" : "HorizontalLayoutSkin",
            "adjustment" : 1,
            "align" : 1,
            "box" : {
               "_typeName" : "RelativeBox",
               "height" : {
                  "_typeName" : "RelativeValue",
                  "type" : 0,
                  "value" : 0
               },
               "offset" : {
                  "_empty" : true
               },
               "width" : {
                  "_typeName" : "RelativeValue",
                  "type" : 0,
                  "value" : 0
               }
            },
            "padding" : {
               "_typeName" : "RelativeValue",
               "type" : 1,
               "value" : 0
            }
         },
         "skipInvisibleElements" : false
      }
   ],
   "position" : {
      "_typeName" : "AligningOffset",
      "horAlign" : 1,
      "horOffset" : {
         "_typeName" : "RelativeValue",
         "type" : 1,
         "value" : 0
      },
      "vertAlign" : 1,
      "vertOffset" : {
         "_typeName" : "RelativeValue",
         "type" : 1,
         "value" : 0
      }
   }
}
