{
   "_typeName" : "StaticFilledRect",
   "_version" : "VER3",
   "box" : {
      "_typeName" : "RelativeBox",
      "height" : {
         "_typeName" : "RelativeValue",
         "type" : 1,
         "value" : 2
      },
      "offset" : {
         "_empty" : true
      },
      "width" : {
         "_typeName" : "RelativeValue",
         "type" : 0,
         "value" : 0
      }
   },
   "color" : [ 0.7200000286102295, 0.8600000143051147, 1, 1 ],
   "position" : {
      "_typeName" : "AligningOffset",
      "horAlign" : 0,
      "horOffset" : {
         "_typeName" : "RelativeValue",
         "type" : 1,
         "value" : 0
      },
      "vertAlign" : 0,
      "vertOffset" : {
         "_typeName" : "RelativeValue",
         "type" : 1,
         "value" : -2
      }
   }
}
